harmonoidmodule/__init__.py
harmonoidmodule/module.py
harmonoidmodule/harmonoidservice/__init__.py
harmonoidmodule/harmonoidservice/async_mutagen.py
harmonoidmodule/harmonoidservice/async_pytube_ytmusicapi.py
harmonoidmodule/harmonoidservice/browsing.py
harmonoidmodule/harmonoidservice/downloading.py
harmonoid_module-1.0.0.2.dist-info/LICENSE
harmonoid_module-1.0.0.2.dist-info/METADATA
harmonoid_module-1.0.0.2.dist-info/WHEEL
harmonoid_module-1.0.0.2.dist-info/top_level.txt
harmonoid_module-1.0.0.2.dist-info/RECORD
