Metadata-Version: 2.1
Name: harmonoid-module
Version: 1.0.0.2
Summary: Harmonoid-service wrapper
Home-page: https://github.com/harmonoid/harmonoid-module
Author: harmonoid Team
License: UNKNOWN
Platform: UNKNOWN
Classifier: Programming Language :: Python :: 3
Classifier: License :: OSI Approved :: MIT License
Classifier: Operating System :: OS Independent
Requires-Python: >=3.6
Requires-Dist: ytmusicapi
Requires-Dist: pytube
Requires-Dist: mutagen
Requires-Dist: aiofiles
Requires-Dist: httpx
